LICENSE.txt
MANIFEST.in
Makefile
README.md
include.mk
requirements.txt
setup.cfg
setup.py
docs/Makefile
docs/epydoc.conf
docs/pmcapi/api-objects.txt
docs/pmcapi/class-tree.html
docs/pmcapi/crarr.png
docs/pmcapi/epydoc.css
docs/pmcapi/epydoc.js
docs/pmcapi/exceptions.AssertionError-class.html
docs/pmcapi/frames.html
docs/pmcapi/help.html
docs/pmcapi/identifier-index.html
docs/pmcapi/index.html
docs/pmcapi/module-tree.html
docs/pmcapi/pololu-module.html
docs/pmcapi/pololu-pysrc.html
docs/pmcapi/pololu.motors-module.html
docs/pmcapi/pololu.motors-pysrc.html
docs/pmcapi/pololu.motors.crc7-module.html
docs/pmcapi/pololu.motors.crc7-pysrc.html
docs/pmcapi/pololu.motors.qik-module.html
docs/pmcapi/pololu.motors.qik-pysrc.html
docs/pmcapi/pololu.motors.qik.Qik-class.html
docs/pmcapi/pololu.motors.qik2s9v1-module.html
docs/pmcapi/pololu.motors.qik2s9v1-pysrc.html
docs/pmcapi/pololu.motors.qik2s9v1.Qik2s9v1-class.html
docs/pmcapi/pololu.motors.tests-module.html
docs/pmcapi/pololu.motors.tests-pysrc.html
docs/pmcapi/pololu.motors.tests.test_qik2s9v1-module.html
docs/pmcapi/pololu.motors.tests.test_qik2s9v1-pysrc.html
docs/pmcapi/pololu.motors.tests.test_qik2s9v1.TestQik2s9v1-class.html
docs/pmcapi/redirect.html
docs/pmcapi/toc-everything.html
docs/pmcapi/toc-pololu-module.html
docs/pmcapi/toc-pololu.motors-module.html
docs/pmcapi/toc-pololu.motors.crc7-module.html
docs/pmcapi/toc-pololu.motors.qik-module.html
docs/pmcapi/toc-pololu.motors.qik2s9v1-module.html
docs/pmcapi/toc-pololu.motors.tests-module.html
docs/pmcapi/toc-pololu.motors.tests.test_qik2s9v1-module.html
docs/pmcapi/toc.html
docs/pmcapi/uml_class_diagram_for_exceptio.gif
docs/pmcapi/uml_class_diagram_for_pololu_m.gif
docs/pmcapi/uml_class_diagram_for_pololu_m_2.gif
docs/pmcapi/uml_class_diagram_for_pololu_m_3.gif
pololu/__init__.py
pololu/motors/__init__.py
pololu/motors/crc7.py
pololu/motors/qik.py
pololu/motors/qik2s9v1.py
pololu_motors.egg-info/PKG-INFO
pololu_motors.egg-info/SOURCES.txt
pololu_motors.egg-info/dependency_links.txt
pololu_motors.egg-info/requires.txt
pololu_motors.egg-info/top_level.txt