Metadata-Version: 1.1
Name: pololu-motors
Version: 0.2.2
Summary: Pololu motor driver APIs.
Home-page: https://github.com/cnobile2012/pololu-motors
Author: Carl J. Nobile
Author-email: carl.nobile@gmail.com
License: MIT
Download-URL: https://github.com/cnobile2012/pololu-motors/tarball/t-v0.2.2
Keywords: pololu motor API
Platform: UNKNOWN
Classifier: License :: OSI Approved :: MIT License
Classifier: Operating System :: OS Independent
Classifier: Programming Language :: Python :: 2.7
Classifier: Topic :: Home Automation
Classifier: Topic :: System :: Hardware :: Hardware Drivers
